osaca/__init__.py
osaca/__main__.py
osaca/db_interface.py
osaca/frontend.py
osaca/osaca.py
osaca/utils.py
osaca/data/.a64fx_115aef67dde223598681acdbc35e0dbe08fbf428e3a68c76d0e6d2b42f137a4f.pickle
osaca/data/.a72_36a1e0040e052903875018f72714fff9084225e6e6b1332994550d7908e6d16d.pickle
osaca/data/.bdw_e5b31d47f4c7be22b5baff4c9468cda42c35e32a7e079f98b723a61b15e62d49.pickle
osaca/data/.csx_f5e6182defbdb7f979706d207080c23a7e8ef986638be2ceb8eb07fd265ed2be.pickle
osaca/data/.hsw_547caf13844e09624294ac198fab53f25bb77e188d67c8f13d2f00080bf6263e.pickle
osaca/data/.icl_41bb4836050b85817839ebe620bf067f4b9eaf7645dd2851aeba24a8685e4b96.pickle
osaca/data/.icx_5c7543ee0204e2212124a427cccf956a6da3a993f3c995f3de691142f81b507a.pickle
osaca/data/.ivb_58ba15ec0b48f620175ca0be4b15e459b3d98b3cd37f597aa7f02f9d0019a1fd.pickle
osaca/data/.m1_71f7ee14d5d4192a0f32ba7677294adca1974030ef71aca9bab7b929245650e9.pickle
osaca/data/.n1_868cf778b3ce9b4cc0a39f1fc327e73763d21ee35eaec295e5d1330f0e129f92.pickle
osaca/data/.skx_1d92379044ab98f2ef3922bd7e3c672015cd16a4c4ccb7ab19480459101b3dfd.pickle
osaca/data/.snb_8964c58b70bdac2983da171b9eb35a8bf36a928144e4b71a98e87cc32a0d1453.pickle
osaca/data/.spr_ea1b97e8903824c8b8ddfcc2f40ea838eb3483cf6ab4da880a1f09047f3857f6.pickle
osaca/data/.tsv110_146f59e7a17b1dd5b9278145c657d8b842bfba331e02abb6b2570957457f86f2.pickle
osaca/data/.tx2_4385bc59fa81adcd4762b23c454082ee82297488bb01ac5c95814eb274b4be7a.pickle
osaca/data/.v2_aab0037b998f0b07ff18ae22b85d226b920db8c0c071881e4e30864aabd6aae5.pickle
osaca/data/.zen1_204232ee263a0fa7a2b8a94644dd315add0bfc76066134df5890fc404940ac33.pickle
osaca/data/.zen2_08ee10688e4b5321169269b841fa9c863ad40717e2014e2adad1cde6c37700d1.pickle
osaca/data/.zen3_54a8c1ed5210e73c889670e6a540c9dec2c8ac341e292c2aed462fa3c1e9cb54.pickle
osaca/data/.zen4_ee481a3ea3e388eb488c194be3e7b7225d3408ad963ba2e3ef55464565ebbc4b.pickle
osaca/data/_build_cache.py
osaca/data/a64fx.yml
osaca/data/a72.yml
osaca/data/bdw.yml
osaca/data/csx.yml
osaca/data/hsw.yml
osaca-0.7.1.dist-info/LICENSE
osaca-0.7.1.dist-info/METADATA
osaca-0.7.1.dist-info/WHEEL
osaca-0.7.1.dist-info/entry_points.txt
osaca-0.7.1.dist-info/top_level.txt
osaca-0.7.1.dist-info/RECORD
