Metadata-Version: 2.1
Name: osaca
Version: 0.7.1
Summary: Open Source Architecture Code Analyzer
Home-page: https://github.com/RRZE-HPC/OSACA
Author: Jan Laukemann
Author-email: jan.laukemann@fau.de
License: AGPLv3
Keywords: hpc performance benchmark analysis architecture
Classifier: Development Status :: 4 - Beta
Classifier: Intended Audience :: Developers
Classifier: Intended Audience :: Science/Research
Classifier: Topic :: Scientific/Engineering
Classifier: Topic :: Software Development
Classifier: Topic :: Utilities
Classifier: License :: OSI Approved :: GNU Affero General Public License v3
Classifier: Programming Language :: Python :: 3
Classifier: Programming Language :: Python :: 3.6
Classifier: Programming Language :: Python :: 3.7
Classifier: Programming Language :: Python :: 3.8
Classifier: Programming Language :: Python :: 3.9
Requires-Python: >=3.6
License-File: LICENSE
Requires-Dist: networkx
Requires-Dist: pyparsing>=2.3.1
Requires-Dist: ruamel.yaml>=0.15.71
